CHANGES
COPYRIGHT
MANIFEST.in
NOTICE
README
TODO
__init__.py
_gviz_api.py
api.py
extfmt.py
proto.py
rpc.py
search.py
setup.cfg
setup.py
stdfmt.py
stdhash.py
ticket.py
timeline.py
util.py
vcs.py
wiki.py
./__init__.py
./_gviz_api.py
./api.py
./extfmt.py
./proto.py
./rpc.py
./search.py
./stdfmt.py
./stdhash.py
./ticket.py
./timeline.py
./util.py
./vcs.py
./wiki.py
./ig/__init__.py
./ig/api.py
./ig/db.py
./ig/web_ui.py
./ig/wiki.py
TracGViz.egg-info/PKG-INFO
TracGViz.egg-info/SOURCES.txt
TracGViz.egg-info/dependency_links.txt
TracGViz.egg-info/entry_points.txt
TracGViz.egg-info/top_level.txt
htdocs/img.jpg
ig/htdocs/icon_home1.png
ig/templates/ig_border_edit.html
messages/es/LC_MESSAGES/trac.mo
templates/gviz_index.html