Metadata-Version: 1.1
Name: TracGViz
Version: 1.3.4
Summary: Trac Data Sources for Google Visualization API. Embed iGoogle gadgets using WikiFormatting.
Home-page: https://opensvn.csie.org/traccgi/swlcu/wiki/En/Devel/TracGViz
Author: Olemis Lang
Author-email: olemis@gmail.com
License: UNKNOWN
Download-URL: http://pypi.python.org/packages/2.5/T/TracGViz/TracGViz-1.3.4-py2.5.egg
Platform: UNKNOWN
Classifier: Development Status :: 3 - Alpha
Classifier: Environment :: Plugins
Classifier: Environment :: Web Environment
Classifier: Framework :: Trac
Classifier: Intended Audience :: Developers
Classifier: Intended Audience :: Information Technology
Classifier: Intended Audience :: Other Audience
Classifier: Intended Audience :: System Administrators
Classifier: License :: OSI Approved :: Apache Software License
Classifier: Natural Language :: English
Classifier: Natural Language :: Spanish
Classifier: Operating System :: OS Independent
Classifier: Programming Language :: Python :: 2.5
Classifier: Programming Language :: Python
Classifier: Topic :: Database
Classifier: Topic :: Internet :: WWW/HTTP :: Dynamic Content :: CGI Tools/Libraries
Classifier: Topic :: Internet :: WWW/HTTP :: HTTP Servers
Classifier: Topic :: Internet :: WWW/HTTP :: WSGI
Classifier: Topic :: Software Development :: Bug Tracking
Classifier: Topic :: Software Development :: Libraries :: Application Frameworks
Classifier: Topic :: Software Development :: Libraries :: Python Modules
Classifier: Topic :: Software Development :: User Interfaces
Classifier: Topic :: Software Development :: Widget Sets
Requires: trac
Requires: tracrpc
Requires: gviz_api
Provides: tracgviz (1.3.4)
Provides: tracgviz.ig (1.3.4)
Obsoletes: tracgviz (>=1.0.0, <1.3.4)
Obsoletes: tracgviz.ig (>=1.0.0, <1.3.4)
